odoo10_addon_stock_picking_line_sequence-10.0.1.2.0-nspkg.pth
odoo/addons/stock_picking_line_sequence/README.rst
odoo/addons/stock_picking_line_sequence/__init__.py
odoo/addons/stock_picking_line_sequence/__manifest__.py
odoo/addons/stock_picking_line_sequence/init_hooks.py
odoo/addons/stock_picking_line_sequence/i18n/ca.po
odoo/addons/stock_picking_line_sequence/i18n/de.po
odoo/addons/stock_picking_line_sequence/i18n/es.po
odoo/addons/stock_picking_line_sequence/i18n/es_MX.po
odoo/addons/stock_picking_line_sequence/i18n/fi.po
odoo/addons/stock_picking_line_sequence/i18n/fr.po
odoo/addons/stock_picking_line_sequence/i18n/hr.po
odoo/addons/stock_picking_line_sequence/i18n/it.po
odoo/addons/stock_picking_line_sequence/i18n/nl_NL.po
odoo/addons/stock_picking_line_sequence/i18n/pt.po
odoo/addons/stock_picking_line_sequence/i18n/pt_BR.po
odoo/addons/stock_picking_line_sequence/i18n/sl.po
odoo/addons/stock_picking_line_sequence/i18n/stock_picking_line_sequence.pot
odoo/addons/stock_picking_line_sequence/i18n/tr.po
odoo/addons/stock_picking_line_sequence/i18n/tr_TR.po
odoo/addons/stock_picking_line_sequence/models/__init__.py
odoo/addons/stock_picking_line_sequence/models/procurement.py
odoo/addons/stock_picking_line_sequence/models/stock.py
odoo/addons/stock_picking_line_sequence/report/report_deliveryslip.xml
odoo/addons/stock_picking_line_sequence/static/description/icon.png
odoo/addons/stock_picking_line_sequence/tests/__init__.py
odoo/addons/stock_picking_line_sequence/tests/test_move_lines_sequence.py
odoo/addons/stock_picking_line_sequence/views/stock_view.xml
odoo10_addon_stock_picking_line_sequence-10.0.1.2.0.dist-info/METADATA
odoo10_addon_stock_picking_line_sequence-10.0.1.2.0.dist-info/WHEEL
odoo10_addon_stock_picking_line_sequence-10.0.1.2.0.dist-info/namespace_packages.txt
odoo10_addon_stock_picking_line_sequence-10.0.1.2.0.dist-info/top_level.txt
odoo10_addon_stock_picking_line_sequence-10.0.1.2.0.dist-info/RECORD
